quapy/__init__.py
quapy/error.py
quapy/evaluation.py
quapy/functional.py
quapy/model_selection.py
quapy/plot.py
quapy/protocol.py
quapy/util.py
quapy/classification/__init__.py
quapy/classification/calibration.py
quapy/classification/methods.py
quapy/classification/neural.py
quapy/classification/svmperf.py
quapy/data/__init__.py
quapy/data/_ifcb.py
quapy/data/_lequa.py
quapy/data/base.py
quapy/data/datasets.py
quapy/data/preprocessing.py
quapy/data/reader.py
quapy/method/__init__.py
quapy/method/_bayesian.py
quapy/method/_kdey.py
quapy/method/_neural.py
quapy/method/_threshold_optim.py
quapy/method/aggregative.py
quapy/method/base.py
quapy/method/composable.py
quapy/method/meta.py
quapy/method/non_aggregative.py
quapy/tests/__init__.py
quapy/tests/test_base.py
quapy/tests/test_datasets.py
quapy/tests/test_evaluation.py
quapy/tests/test_hierarchy.py
quapy/tests/test_labelcollection.py
quapy/tests/test_methods.py
quapy/tests/test_modsel.py
quapy/tests/test_protocols.py
quapy/tests/test_replicability.py
QuaPy-0.1.9.dist-info/LICENSE
QuaPy-0.1.9.dist-info/METADATA
QuaPy-0.1.9.dist-info/WHEEL
QuaPy-0.1.9.dist-info/top_level.txt
QuaPy-0.1.9.dist-info/RECORD
