Metadata-Version: 2.1
Name: QuaPy
Version: 0.1.9
Summary: QuaPy: a framework for Quantification in Python
Home-page: https://github.com/HLT-ISTI/QuaPy
Maintainer: Alejandro Moreo
Maintainer-email: alejandro.moreo@isti.cnr.it
Project-URL: Contributors, https://github.com/HLT-ISTI/QuaPy/graphs/contributors
Project-URL: Bug Reports, https://github.com/HLT-ISTI/QuaPy/issues
Project-URL: Wiki, https://github.com/HLT-ISTI/QuaPy/wiki
Project-URL: Documentation, https://hlt-isti.github.io/QuaPy/
Project-URL: Source, https://github.com/HLT-ISTI/QuaPy/
Keywords: machine learning,quantification,classification,prevalence estimation,priors estimate
Classifier: Development Status :: 4 - Beta
Classifier: Intended Audience :: Developers
Classifier: Intended Audience :: Science/Research
Classifier: Programming Language :: Python
Classifier: Topic :: Software Development
Classifier: Topic :: Scientific/Engineering
Classifier: License :: OSI Approved :: BSD License
Classifier: Programming Language :: Python :: 3
Classifier: Programming Language :: Python :: 3.8
Classifier: Programming Language :: Python :: 3.9
Classifier: Programming Language :: Python :: 3 :: Only
Requires-Python: >=3.8, <4
License-File: LICENSE
Requires-Dist: scikit-learn
Requires-Dist: pandas
Requires-Dist: tqdm
Requires-Dist: matplotlib
Requires-Dist: joblib
Requires-Dist: xlrd
Requires-Dist: abstention
Requires-Dist: ucimlrepo
Requires-Dist: certifi
Provides-Extra: bayes
Requires-Dist: jax; extra == "bayes"
Requires-Dist: jaxlib; extra == "bayes"
Requires-Dist: numpyro; extra == "bayes"
Provides-Extra: docs
Requires-Dist: sphinx-rtd-theme; extra == "docs"
Requires-Dist: myst-parser; extra == "docs"
Provides-Extra: neural
Requires-Dist: torch; extra == "neural"
Provides-Extra: tests
Requires-Dist: certifi; extra == "tests"
